tpsisar18/__init__.py
tpsisar18/topsis.py
tpsisar18-0.0.2.dist-info/LICENSE
tpsisar18-0.0.2.dist-info/METADATA
tpsisar18-0.0.2.dist-info/WHEEL
tpsisar18-0.0.2.dist-info/top_level.txt
tpsisar18-0.0.2.dist-info/RECORD
