Metadata-Version: 2.1
Name: tpsisar18
Version: 0.0.2
Summary: A small package that showcases topsis approach
Home-page: https://github.com/aryansindhi18/topsis_approach-aryansindhi18.git
Author: Aryan Sindhi,Simarpreet Singh,Aryan Bhatia
Author-email: asindhi_be17@thapar.edu
License: UNKNOWN
Platform: UNKNOWN
Classifier: Programming Language :: Python :: 3
Classifier: License :: OSI Approved :: MIT License
Classifier: Operating System :: OS Independent
Requires-Python: >=3.6
